SpaGCN/SpaGCN.py
SpaGCN/__init__.py
SpaGCN/calculate_adj.py
SpaGCN/calculate_moran_I.py
SpaGCN/ez_mode.py
SpaGCN/layers.py
SpaGCN/models.py
SpaGCN/util.py
SpaGCN-1.2.7.dist-info/License
SpaGCN-1.2.7.dist-info/METADATA
SpaGCN-1.2.7.dist-info/WHEEL
SpaGCN-1.2.7.dist-info/top_level.txt
SpaGCN-1.2.7.dist-info/RECORD
