Metadata-Version: 2.1
Name: SpaGCN
Version: 1.2.7
Summary: SpaGCN: Integrating gene expression and histology to identify spatial domains and spatially variable genes using graph convolutional networks
Home-page: https://github.com/jianhuupenn/SpaGCN
Author: Jian Hu
Author-email: jianhu@pennmedicine.upenn.edu
Classifier: Programming Language :: Python :: 3
Classifier: License :: OSI Approved :: MIT License
Classifier: Operating System :: OS Independent
Requires-Python: >=3.6
License-File: License
Requires-Dist: python-igraph
Requires-Dist: torch
Requires-Dist: pandas
Requires-Dist: numpy
Requires-Dist: scipy
Requires-Dist: scanpy
Requires-Dist: anndata
Requires-Dist: louvain
Requires-Dist: scikit-learn
Requires-Dist: numba
